{
  "BackOrderFilterType": {
    "children": [
      {"type":"OPT", "label":"global.bo.only", "value":"INCLUDE"},
      {"type":"OPT", "label":"global.exclude.bo", "value":"EXCLUDE"}
    ]
  },
  "ChargeMethodType": {
    "children": [
      {"type":"OPT", "label":"global.quantity", "value":"Q"},
      {"type":"OPT", "label":"global.weight", "value":"W"},
      {"type":"OPT", "label":"global.cube", "value":"C"}
    ]
  },
  "CutOffType": {
    "children": [
      {"type":"OPT", "label":"global.add", "value":"+"},
      {"type":"OPT", "label":"global.subtract", "value":"-"},
      {"type":"OPT", "label":"global.ignore", "value":"" }
    ]
  },
  "CutStatusType": {
    "children": [
      {"type":"OPT", "label":"global.available", "value":"a"},
      {"type":"OPT", "label":"global.cut", "value":"c"},
      {"type":"OPT", "label":"global.quoted", "value":"q"},
      {"type":"OPT", "label":"global.reserved", "value":"r"},
      {"type":"OPT", "label":"global.sold", "value":"s"},
      {"type":"OPT", "label":"global.transfer", "value":"t"},
      {"type":"OPT", "label":"global.unavailable", "value":"u"}
    ]
  },
  "DestinationType": {
    "children": [
      {"type":"OPT", "label":"global.vendor", "value":"v"},
      {"type":"OPT", "label":"global.warehouse", "value":"w"},
      {"type":"OPT", "label":"global.final.step", "value":"f"}
    ]
  },
  "DispositionType": {
    "children": [
      {"type":"OPT", "label":"global.none", "value":""},
      {"type":"OPT", "label":"global.ship.complete", "value":"s"}
    ]
  },
  "FinishedProductType": {
    "children": [
      {"type":"OPT", "label":"global.product", "value":2},
      {"type":"OPT", "label":"global.group", "value":1}
    ]
  },
  "FinishedProductLineType": {
    "children": [
      {"type":"OPT", "label":"global.stock", "value":""},
      {"type":"OPT", "label":"global.non.stock", "value":"n"},
      {"type":"OPT", "label":"global.special", "value":"s"}
    ]
  },
  "InventoryReceiptStageType": {
    "children": [
      {"type":"OPT", "label":"global.open", "value":"1"},
      {"type":"OPT", "label":"global.printed", "value":"3"},
      {"type":"OPT", "label":"global.open.to.printed", "value":"9"}
    ]
  },
  "LaborType": {
    "children": [
      {"type":"OPT", "label":"global.quantity", "value":"Q"},
      {"type":"OPT", "label":"global.weight", "value":"W"},
      {"type":"OPT", "label":"global.cube", "value":"C"}
    ]
  },
  "LineType": {
    "children": [
      {"type":"OPT", "label":"global.non.stock", "value":"n"},
      {"type":"OPT", "label":"global.stock", "value":""}
    ]
  },
  "NonSpecificationPrintType": {
    "children": [
      {"type":"OPT", "label":"global.yes", "value":"Y"},
      {"type":"OPT", "label":"global.no", "value":"N"}
    ]
  },
  "NonStockType": {
    "children": [
      {"type":"OPT", "label":"global.stock", "value":""},
      {"type":"OPT", "label":"global.non.stock", "value":"N"},
      {"type":"OPT", "label":"global.special", "value":"S"},
      {"type":"OPT", "label":"global.configuration", "value":"C"}
    ]
  },
  "OrderStageFullVaeh": {
    "children": [
      {"type":"OPT", "label":"global.all", "value":-1},
      {"type":"OPT", "label":"global.entered", "value":0},
      {"type":"OPT", "label":"global.ordered", "value":1},
      {"type":"OPT", "label":"global.printed", "value":3},
      {"type":"OPT", "label":"global.received", "value":5}
    ]
  },
  "PrintOrder": {
    "children": [
      {"type":"OPT", "label":"global.route", "value":"true"},
      {"type":"OPT", "label":"global.order.number", "value":"false"}
    ]
  },
  "PrintReceiptType": {
     "children":[
      {"type":"OPT", "label":"global.print", "value":"p"},
      {"type":"OPT", "label":"global.file", "value":"f"},
      {"type":"OPT", "label":"global.device", "value":"d"}
     ]
  },
  "RuleEqualityType": {
    "children": [
      {"type":"OPT", "label":"global.is.equal.to", "value":"="},
      {"type":"OPT", "label":"global.is.not.equal.to", "value":"<>"},
      {"type":"OPT", "label":"global.is.greater.than", "value":">"},
      {"type":"OPT", "label":"global.is.greater.than.or.equal.to", "value":">="},
      {"type":"OPT", "label":"global.less.than", "value":"<"},
      {"type":"OPT", "label":"global.less.than.or.", "value":"<="}
    ]
  },
  "RuleUnion": {
      "children": [
         {"type":"OPT", "label":"global.and", "value":true},
         {"type":"OPT", "label":"global.or", "value":false}
      ]
   },
  "SectionStageCodeType": {
    "children": [
      {"type":"OPT", "label":"global.open", "value":1},
      {"type":"OPT", "label":"global.printed", "value":3},
      {"type":"OPT", "label":"global.shipped", "value":5},
      {"type":"OPT", "label":"global.complete", "value":7},
      {"type":"OPT", "label":"global.paid", "value":8},
      {"type":"OPT", "label":"global.cancelled", "value":9}
    ]
  },
  "SectionType": {
    "children": [
      {"type":"OPT", "label":"global.specification", "value":"SP"},
      {"type":"OPT", "label":"global.inventory.component", "value":"IN"},
      {"type":"OPT", "label":"global.external", "value":"EX"},
      {"type":"OPT", "label":"global.internal", "value":"IT"},
      {"type":"OPT", "label":"global.inspection", "value":"IS"},
      {"type":"OPT", "label":"global.inventory.in", "value":"II"}
    ]
  },
  "SegmentType": {
    "children": [
      {"type":"OPT", "label":"global.character", "value":"C"},
      {"type":"OPT", "label":"global.number", "value":"D"},
      {"type":"OPT", "label":"global.integer", "value":"I"}
    ]
  },
  "ShippingStageType": {
    "children": [
      {"type":"OPT", "label":"global.open", "value":"1"},
      {"type":"OPT", "label":"global.printed", "value":"3"},
      {"type":"OPT", "label":"global.open.to.printed", "value":"9"},
      {"type":"OPT", "label":"global.shipped", "value":"5"}
    ]
  },
  "SpecificationPrintType": {
    "children": [
      {"type":"OPT", "label":"global.external", "value":"E"},
      {"type":"OPT", "label":"global.internal", "value":"I"},
      {"type":"OPT", "label":"global.both", "value":"B"},
      {"type":"OPT", "label":"global.neither", "value":"N"}
    ]
  },
  "StageCodeType": {
    "children": [
      {"type":"OPT", "label":"global.entered", "value":0},
      {"type":"OPT", "label":"global.ordered", "value":1},
      {"type":"OPT", "label":"global.printed", "value":3},
      {"type":"OPT", "label":"global.received", "value":5},
      {"type":"OPT", "label":"global.closed", "value":7},
      {"type":"OPT", "label":"global.cancelled", "value":9}
    ]
  },
  "StageType": {
    "children": [
      {"type":"OPT", "label":"global.all", "value":""},
      {"type":"OPT", "label":"global.entered", "value":"0"},
      {"type":"OPT", "label":"global.ordered", "value":"1"},
      {"type":"OPT", "label":"global.printed", "value":"3"},
      {"type":"OPT", "label":"global.received", "value":"5"},
      {"type":"OPT", "label":"global.closed", "value":"7"},
      {"type":"OPT", "label":"global.cancelled", "value":"9"}
    ]
  },
  "TimeType": {
    "children": [
      {"type":"OPT", "label":"global.actual", "value":"a"},
      {"type":"OPT", "label":"global.estimated", "value":"e"},
      {"type":"OPT", "label":"global.variable", "value":"v"}
    ]
  },
  "TimeTypeNoVar": {
    "children": [
      {"type":"OPT", "label":"global.actual", "value":"a"},
      {"type":"OPT", "label":"global.estimated", "value":"e"}
    ]
  },
  "TransferTransactionType": {
    "children": [
      {"type":"OPT", "label":"global.all", "value":""},
      {"type":"OPT", "label":"global.value.add", "value":"VA"},
      {"type":"OPT", "label":"global.direct.order", "value":"DO"},
      {"type":"OPT", "label":"global.quote", "value":"QU"}
    ]
  },
  "VaLineCancelType": {
    "children": [
      {"type":"OPT", "label":"global.do.not.cancel", "value":""},
      {"type":"OPT", "label":"global.prorate.as.is", "value":"I"},
      {"type":"OPT", "label":"global.recalculate.proration", "value":"C"},
      {"type":"OPT", "label":"global.remove.proration", "value":"R"}
    ]
  },
  "VaLinesEntryType": {
    "children": [
      {"type":"OPT", "label":"global.group", "value":1},
      {"type":"OPT", "label":"global.product", "value":2}
    ]
  },
  "VAOrderTransactionType": {
    "children": [
      {"type":"OPT", "label":"global.value.add", "value":"va"},
      {"type":"OPT", "label":"global.direct.order", "value":"da"},
      {"type":"OPT", "label":"global.quote", "value":"qu"}
    ]
  },
  "VARollupType": {
    "children": [
      {"type":"OPT", "label":"global.margin", "value":"margin"},
      {"type":"OPT", "label":"global.markup", "value":"markup"}
    ]
  },
  "VAUpdateTypes": {
    "children": [
      {"type":"OPT", "label":"global.order", "value":"O"},
      {"type":"OPT", "label":"global.warehouse.transfer", "value":"T"},
      {"type":"OPT", "label":"global.fab.va", "value":"F"},
      {"type":"OPT", "label":"global.work.order", "value":"W" }
    ]
  },
  "VASourceOrderTypes": {
    "children": [
      {"type":"OPT", "label":"global.no.tie", "value":"n"},
      {"type":"OPT", "label":"global.purchase.order", "value":"p"},
      {"type":"OPT", "label":"global.warehouse.transfer", "value":"t"},
      {"type":"OPT", "label":"global.value.add", "value":"f" }
    ]
  },
  "VABackOrderTypes": {
    "children": [
      {"type":"OPT", "label":"global.direct", "value":"d"},
      {"type":"OPT", "label":"global.allow.back.order", "value":"y"}
    ]
  },
  "VASourceBackTieTypes": {
    "children": [
      {"type":"OPT", "label":"global.neither", "value":"n"},
      {"type":"OPT", "label":"global.purchase.order", "value":"p"},
      {"type":"OPT", "label":"global.warehouse.transfer", "value":"t"}
    ]
  },
  "VAHeaderTiesOrderTypes": {
    "children": [
      {"type":"OPT", "label":"global.order", "value":"Order"},
      {"type":"OPT", "label":"global.warehouse.transfer", "value":"Transfer"},
      {"type":"OPT", "label":"global.fab.va", "value":"Fab VA"},
      {"type":"OPT", "label":"global.work.order", "value":"Work Order"}
    ]
  }
}
