{
  "viewId": "po-poip-detail-tabs-header",
  "id": 1,
  "type": "VIEW",
  "subType": "",
  "children": [
    {
      "id": 2,
      "type": "EXP_AREA",
      "label": "global.general",
      "children": [
        {
          "id": 3,
          "type": "ROW",
          "children": [
            {
              "id": 4,
              "type": "COL",
              "subType": "1/3",
              "children": [
                {
                  "id": 7,
                  "type": "FIELD",
                  "subType": "INFO",
                  "model": "pdhc.poeh.vendno",
                  "label": "global.vendor.number",
                  "dataDesc": "pdhc.vendname",
                  "hyperlinks": {
                    "data": {
                      "stateRef": "apiv.detail({pk: pdhc.poeh.vendno, pk2: pdhc.poeh.shipfmno})"
                    }
                  }
                },
                {
                  "id": 11,
                  "type": "FIELD",
                  "subType": "INFO",
                  "model": "pdhc.poeh.whse",
                  "label": "global.to"
                },
                {
                  "id": 14,
                  "type": "FIELD",
                  "subType": "INFO",
                  "model": "pdhc.poeh.billtowhse",
                  "label": "global.bill."
                },
                {
                  "id": 17,
                  "type": "FIELD",
                  "subType": "INFO",
                  "model": "pdhc.freightterms",
                  "label": "global.freight.terms"
                },
                {
                  "id": 20,
                  "type": "FIELD",
                  "subType": "INFO",
                  "model": "pdhc.poeh.frtbillacct",
                  "label": "global.freight.bill.account"
                },
                {
                  "id": 24,
                  "type": "FIELD",
                  "subType": "INFO",
                  "model": "pdhc.backorder",
                  "label": "global.back.order",
                  "labelHidden": true
                }
              ]
            },
            {
              "id": 6,
              "type": "COL",
              "subType": "1/3",
              "children": [
                {
                  "id": 10,
                  "type": "FIELD",
                  "subType": "INFO",
                  "model": "pdhc.poeh.shipfmno",
                  "label": "global.ship.from",
                  "hyperlinks": {
                    "data": {
                      "stateRef": "apiv.detail({pk: pdhc.poeh.vendno, pk2: pdhc.poeh.shipfmno})"
                    }
                  }
                },
                {
                  "id": 12,
                  "type": "FIELD",
                  "subType": "INFO",
                  "model": "pdhc.vendtype",
                  "label": "global.vendor.type"
                },
                {
                  "id": 15,
                  "type": "FIELD",
                  "subType": "INFO",
                  "model": "pdhc.poeh.transtype",
                  "label": "global.type",
                  "dataFormat": "PoOrderType"
                },
                {
                  "id": 18,
                  "type": "FIELD",
                  "subType": "INFO",
                  "model": "pdhc.poeh.approvty",
                  "label": "global.approval"
                },
                {
                  "id": 21,
                  "type": "FIELD",
                  "subType": "INFO",
                  "model": "pdhc.poeh.vendordno",
                  "label": "global.suppliers.order.number"
                },
                {
                  "id": 25,
                  "type": "FIELD",
                  "subType": "INFO",
                  "model": "pdhc.rush",
                  "label": "global.rush",
                  "labelHidden": true
                },
                {
                  "id": 153,
                  "type": "FIELD",
                  "subType": "DROP_DOWN",
                  "model": "pdhc.poheader.netbillty",
                  "label": "global.net.billed",
                  "type3": "SET",
                  "metaGroup": "COMMON",
                  "meta": "NetBillType",
                  "readonly": true
                }
              ]
            },
            {
              "id": 5,
              "type": "COL",
              "subType": "1/3",
              "children": [
                {
                  "id": 8,
                  "type": "FIELD",
                  "subType": "INFO",
                  "model": "pdhc.poeh.prodline",
                  "label": "global.line"
                },
                {
                  "id": 13,
                  "type": "FIELD",
                  "subType": "INFO",
                  "model": "pdhc.poeh.stagecd",
                  "label": "global.stage",
                  "dataFormat": "PoStage"
                },
                {
                  "id": 16,
                  "type": "FIELD",
                  "subType": "INFO",
                  "model": "pdhc.poeh.buyer",
                  "label": "global.buyer"
                },
                {
                  "id": 19,
                  "type": "FIELD",
                  "subType": "INFO",
                  "model": "pdhc.poeh.transferloc",
                  "label": "global.transfer.location"
                },
                {
                  "id": 22,
                  "type": "FIELD",
                  "subType": "INFO",
                  "model": "pdhc.correctiontype",
                  "label": "global.correction.type",
                  "labelHidden": true
                },
                {
                  "id": 26,
                  "type": "FIELD",
                  "subType": "INFO",
                  "model": "pdhc.currencyDescrip",
                  "label": "global.currency.code",
                  "labelHidden": true
                }
              ]
            }
          ]
        }
      ]
    },
    {
      "id": 27,
      "type": "EXP_AREA",
      "label": "global.record.info",
      "children": [
        {
          "id": 28,
          "type": "ROW",
          "children": [
            {
              "id": 29,
              "type": "COL",
              "subType": "1/3",
              "children": [
                {
                  "id": 32,
                  "type": "FIELD",
                  "subType": "INFO",
                  "model": "pdhc.poheader.createdby",
                  "label": "global.created.by"
                },
                {
                  "id": 35,
                  "type": "FIELD",
                  "subType": "INFO",
                  "model": "pdhc.poheader.receiverno",
                  "label": "global.receiver.number"
                },
                {
                  "id": 152,
                  "type": "FIELD",
                  "subType": "INFO",
                  "model": "pdhc.poheader.vendretauth",
                  "label": "global.vendor.return.authorization.no"
                }
              ]
            },
            {
              "id": 31,
              "type": "COL",
              "subType": "1/3",
              "children": [
                {
                  "id": 33,
                  "type": "FIELD",
                  "subType": "INFO",
                  "model": "pdhc.poheader.rcvoperinit",
                  "label": "global.rcv.oper"
                },
                {
                  "id": 36,
                  "type": "FIELD",
                  "subType": "INFO",
                  "model": "pdhc.poheader.openinit",
                  "label": "global.open.oper"
                }
              ]
            },
            {
              "id": 30,
              "type": "COL",
              "subType": "1/3",
              "children": [
                {
                  "id": 34,
                  "type": "FIELD",
                  "subType": "INFO",
                  "model": "pdhc.poheader.contactname",
                  "label": "global.job.id",
                  "dataDesc": "pdhc.poheader.jmjobid"
                },
                {
                  "id": 37,
                  "type": "FIELD",
                  "subType": "INFO",
                  "model": "pdhc.poheader.crreasonty",
                  "label": "global.return.reason",
                  "dataDesc": "pdhc.poheader.crreasontydesc"
                }
              ]
            }
          ]
        }
      ]
    },
    {
      "id": 38,
      "type": "EXP_AREA",
      "label": "global.ack.info",
      "children": [
        {
          "id": 39,
          "type": "ROW",
          "children": [
            {
              "id": 40,
              "type": "COL",
              "subType": "1/3",
              "children": [
                {
                  "id": 43,
                  "type": "FIELD",
                  "subType": "INFO",
                  "model": "pdhc.poheader.ackdt",
                  "label": "global.acknowledge.date",
                  "dataFormat": "DATE"
                },
                {
                  "id": 46,
                  "type": "FIELD",
                  "subType": "INFO",
                  "model": "pdhc.poheader.acktype",
                  "label": "global.ack.type"
                },
                {
                  "id": 49,
                  "type": "FIELD",
                  "subType": "INFO",
                  "model": "pdhc.poheader.refer",
                  "label": "global.refer"
                },
                {
                  "id": 52,
                  "type": "FIELD",
                  "subType": "INFO",
                  "model": "pdhc.poheader.termstype",
                  "label": "global.terms",
                  "dataDesc": "pdhc.poheader.termstypedesc"
                }
              ]
            },
            {
              "id": 41,
              "type": "COL",
              "subType": "1/3",
              "children": [
                {
                  "id": 155,
                  "type": "FIELD",
                  "subType": "INFO",
                  "model": "pdhc.poheader.ackrsn",
                  "label": "global.ack.reason",
                  "dataFormat": "PoAcknowledgementType"
                },
                {
                  "id": 45,
                  "type": "FIELD",
                  "subType": "INFO",
                  "model": "pdhc.poheader.ackoper",
                  "label": "global.ack.user"
                },
                {
                  "id": 50,
                  "type": "FIELD",
                  "subType": "INFO",
                  "model": "pdhc.oevanumber",
                  "label": "global.tied.oe.va.number",
                  "hyperlinks": {
                    "data": {
                      "stateRef": "oeio.detail({pk:pdhc.poheader.orderaltno, pk2:pdhc.poheader.orderaltsuf})"
                    }
                  }
                },
                {
                  "id": 53,
                  "type": "FIELD",
                  "subType": "INFO",
                  "model": "pdhc.poheader.jrnlno",
                  "label": "global.rcv.journal.number",
                  "dataDesc": "pdhc.poheader.receivemessage",
                  "hyperlinks": {
                    "data": {
                      "stateRef": "glij.detail({pk:pdhc.poeh.jrnlno})"
                    }
                  }
                }
              ]
            },
            {
              "id": 42,
              "type": "COL",
              "subType": "1/3",
              "children": [
                {
                  "id": 47,
                  "type": "FIELD",
                  "subType": "INFO",
                  "model": "pdhc.poheader.shipinstr",
                  "label": "global.instructions"
                },
                {
                  "id": 51,
                  "type": "FIELD",
                  "subType": "INFO",
                  "model": "pdhc.poheader.shipviaty",
                  "label": "global.ship",
                  "dataDesc": "pdhc.poheader.shipviadesc"
                },
                {
                  "id": 48,
                  "type": "FIELD",
                  "subType": "INFO",
                  "model": "pdhc.poheader.extshipinstr",
                  "label": "global.extended.shipping.instructions"
                }
              ]
            }
          ]
        }
      ]
    },
    {
      "id": 54,
      "type": "EXP_AREA",
      "label": "global.status",
      "children": [
        {
          "id": 55,
          "type": "ROW",
          "children": [
            {
              "id": 56,
              "type": "COL",
              "subType": "1/3",
              "children": [
                {
                  "id": 59,
                  "type": "FIELD",
                  "subType": "INFO",
                  "model": "pdhc.poheader.rushfl",
                  "label": "global.rush",
                  "dataFormat": "BooleanToYesNo"
                },
                {
                  "id": 62,
                  "type": "FIELD",
                  "subType": "INFO",
                  "model": "pdhc.poheader.ignoreltfl",
                  "label": "global.ignore.lead.time",
                  "dataFormat": "BooleanToYesNo"
                },
                {
                  "id": 65,
                  "type": "FIELD",
                  "subType": "INFO",
                  "model": "pdhc.poheader.resalefl",
                  "label": "global.resale",
                  "dataFormat": "BooleanToYesNo"
                }
              ]
            },
            {
              "id": 58,
              "type": "COL",
              "subType": "1/3",
              "children": [
                {
                  "id": 60,
                  "type": "FIELD",
                  "subType": "INFO",
                  "model": "pdhc.poheader.confirmfl",
                  "label": "global.confirm",
                  "dataFormat": "BooleanToYesNo"
                },
                {
                  "id": 63,
                  "type": "FIELD",
                  "subType": "INFO",
                  "model": "pdhc.poheader.subfl",
                  "label": "global.subs.ok",
                  "dataFormat": "BooleanToYesNo"
                },
                {
                  "id": 66,
                  "type": "FIELD",
                  "subType": "INFO",
                  "model": "pdhc.poheader.resaleno",
                  "label": "global.resale.number"
                }
              ]
            },
            {
              "id": 57,
              "type": "COL",
              "subType": "1/3",
              "children": [
                {
                  "id": 61,
                  "type": "FIELD",
                  "subType": "INFO",
                  "model": "pdhc.poheader.fobfl",
                  "label": "global.free.on.board.destination",
                  "dataFormat": "BooleanToYesNo"
                },
                {
                  "id": 64,
                  "type": "FIELD",
                  "subType": "INFO",
                  "model": "pdhc.poheader.bofl",
                  "label": "b.o.ok",
                  "dataFormat": "BooleanToYesNo"
                },
                {
                  "id": 67,
                  "type": "FIELD",
                  "subType": "INFO",
                  "model": "pdhc.poheader.jmjobid",
                  "label": "global.contact",
                  "dataDesc": "pdhc.poheader.jmjobrevno"
                }
              ]
            }
          ]
        }
      ]
    },
    {
      "id": 68,
      "type": "EXP_AREA",
      "label": "global.vendor.information",
      "children": [
        {
          "id": 69,
          "type": "ROW",
          "children": [
            {
              "id": 70,
              "type": "COL",
              "subType": "1/3",
              "children": [
                {
                  "id": 74,
                  "type": "FIELD",
                  "subType": "INFO",
                  "model": "pdhc.poheader.vendorname",
                  "label": "global.vendor.number",
                  "hyperlinks": {
                    "data": {
                      "stateRef": "apiv.detail({pk: pdhc.poeh.vendno, pk2: pdhc.poeh.shipfmno})"
                    }
                  }
                }
              ]
            },
            {
              "id": 72,
              "type": "COL",
              "subType": "1/3",
              "children": [
                {
                  "id": 75,
                  "type": "CUSTOM",
                  "subType": "AddressInfo",
                  "options": {
                    "countryCdVisible": true,
                    "addressLabel": "global.address",
                    "addr1Model": "pdhc.poheader.vendoraddr1",
                    "addr2Model": "pdhc.poheader.vendoraddr2",
                    "addr3Model": "pdhc.poheader.vendoraddr3",
                    "cityModel": "pdhc.poheader.vendorcity",
                    "stateModel": "pdhc.poheader.vendorstate",
                    "countryCodeModel": "pdhc.poheader.vendorcountrycd",
                    "zipCodeModel": "pdhc.poheader.vendorzip"
                  }
                }
              ]
            },
            {
              "id": 71,
              "type": "COL",
              "subType": "1/3",
              "children": [
                {
                  "id": 73,
                  "type": "FIELD",
                  "subType": "INFO",
                  "model": "pdhc.poheader.vendorphone",
                  "label": "global.phone.number",
                  "dataFormat": "PHONE"
                },
                {
                  "id": 76,
                  "type": "FIELD",
                  "subType": "INFO",
                  "model": "pdhc.poheader.vendorfax",
                  "label": "global.fax.number"
                }
              ]
            }
          ]
        }
      ]
    },
    {
      "id": 77,
      "type": "EXP_AREA",
      "label": "global.ship.date.info",
      "children": [
        {
          "id": 81,
          "type": "ROW",
          "children": [
            {
              "id": 82,
              "type": "COL",
              "subType": "1/3",
              "children": [
                {
                  "id": 85,
                  "type": "FIELD",
                  "subType": "INFO",
                  "model": "pdhc.poheader.reqshipdt",
                  "label": "global.req.ship.date",
                  "dataFormat": "DATE"
                },
                {
                  "id": 88,
                  "type": "FIELD",
                  "subType": "INFO",
                  "model": "pdhc.poheader.daysold",
                  "label": "global.days.old"
                }
              ]
            },
            {
              "id": 84,
              "type": "COL",
              "subType": "1/3",
              "children": [
                {
                  "id": 86,
                  "type": "FIELD",
                  "subType": "INFO",
                  "model": "pdhc.poheader.expshipdt",
                  "label": "global.expected.ship.date",
                  "dataFormat": "DATE"
                },
                {
                  "id": 156,
                  "type": "FIELD",
                  "subType": "INFO",
                  "model": "pdhc.poheader.podoshipdt",
                  "label": "global.ship.date.for.tied.order",
                  "dataFormat": "DATE"
                }
              ]
            },
            {
              "id": 83,
              "type": "COL",
              "subType": "1/3",
              "children": [
                {
                  "id": 87,
                  "type": "FIELD",
                  "subType": "INFO",
                  "model": "pdhc.poheader.orderdispdesc",
                  "label": "global.order.disposition"
                }
              ]
            }
          ]
        }
      ]
    },
    {
      "id": 89,
      "type": "EXP_AREA",
      "label": "global.additional.info.whse.details",
      "collapsed": true,
      "children": [
        {
          "id": 92,
          "type": "FIELD_SET",
          "label": "global.ship.to",
          "children": [
            {
              "id": 93,
              "type": "ROW",
              "children": [
                {
                  "id": 94,
                  "type": "COL",
                  "subType": "1/3",
                  "children": [
                    {
                      "id": 97,
                      "type": "FIELD",
                      "subType": "INFO",
                      "model": "pdhc.poheaderwhse.whse",
                      "label": "global.warehouse"
                    },
                    {
                      "id": 98,
                      "type": "FIELD",
                      "subType": "INFO",
                      "model": "pdhc.poheaderwhse.shiptonm",
                      "label": "global.name"
                    }
                  ]
                },
                {
                  "id": 96,
                  "type": "COL",
                  "subType": "1/3",
                  "children": [
                    {
                      "id": 99,
                      "type": "CUSTOM",
                      "subType": "AddressInfo",
                      "options": {
                        "countryCdVisible": true,
                        "addressLabel": "global.address",
                        "addr1Model": "pdhc.poheaderwhse.shiptoaddr1",
                        "addr2Model": "pdhc.poheaderwhse.shiptoaddr2",
                        "addr3Model": "pdhc.poheaderwhse.shiptoaddr3",
                        "cityModel": "pdhc.poheaderwhse.shiptocity",
                        "stateModel": "pdhc.poheaderwhse.shiptost",
                        "zipCodeModel": "pdhc.poheaderwhse.shiptozip",
                        "countryCodeModel": "pdhc.poheaderwhse.countrycd"
                      }
                    }
                  ]
                },
                {
                  "id": 95,
                  "type": "COL",
                  "subType": "1/3",
                  "children": [
                    {
                      "id": 100,
                      "type": "FIELD",
                      "subType": "INFO",
                      "model": "pdhc.poheaderwhse.shiptophone",
                      "label": "global.phone.number",
                      "dataFormat": "PHONE"
                    }
                  ]
                }
              ]
            }
          ]
        },
        {
          "id": 107,
          "type": "FIELD_SET",
          "label": "global.bill.to",
          "children": [
            {
              "id": 108,
              "type": "ROW",
              "children": [
                {
                  "id": 109,
                  "type": "COL",
                  "subType": "1/3",
                  "children": [
                    {
                      "id": 112,
                      "type": "FIELD",
                      "subType": "INFO",
                      "model": "pdhc.poheaderwhse.billtowhse",
                      "label": "global.bill.to.warehouse"
                    },
                    {
                      "id": 113,
                      "type": "FIELD",
                      "subType": "INFO",
                      "model": "pdhc.poheaderwhse.billtoname",
                      "label": "global.name"
                    }
                  ]
                },
                {
                  "id": 111,
                  "type": "COL",
                  "subType": "1/3",
                  "children": [
                    {
                      "id": 114,
                      "type": "CUSTOM",
                      "subType": "AddressInfo",
                      "options": {
                        "countryCdVisible": true,
                        "addressLabel": "global.address",
                        "addr1Model": "pdhc.poheaderwhse.billtoaddr1",
                        "addr2Model": "pdhc.poheaderwhse.billtoaddr2",
                        "addr3Model": "pdhc.poheaderwhse.billtoaddr3",
                        "cityModel": "pdhc.poheaderwhse.billtocity",
                        "stateModel": "pdhc.poheaderwhse.billtost",
                        "zipCodeModel": "pdhc.poheaderwhse.billtozip",
                        "countryCodeModel": "pdhc.poheaderwhse.billtocountrycd"
                      }
                    }
                  ]
                },
                {
                  "id": 110,
                  "type": "COL",
                  "subType": "1/3",
                  "children": [
                    {
                      "id": 115,
                      "type": "FIELD",
                      "subType": "INFO",
                      "model": "pdhc.poheaderwhse.billtophoneno",
                      "label": "global.phone.number",
                      "dataFormat": "PHONE"
                    }
                  ]
                }
              ]
            }
          ]
        }
      ]
    },
    {
      "id": 116,
      "type": "EXP_AREA",
      "label": "global.additional.info.misc.details",
      "collapsed": true,
      "children": [
        {
          "id": 128,
          "type": "FIELD_SET",
          "label": "global.qty.info",
          "children": [
            {
              "id": 127,
              "type": "FIELD",
              "subType": "INFO",
              "model": "pdhc.poheadermisc.note",
              "label": "global.quantity.note"
            },
            {
              "id": 119,
              "type": "GRID",
              "model": "pdhc.quantities",
              "options": {
                "paging": false,
                "showRowCount": false
              },
              "controls": {
                "toolbar": {
                  "id": 120,
                  "type": "TOOLBAR",
                  "label": "global.quantities"
                }
              },
              "children": [
                {
                  "id": 121,
                  "type": "GRID_COL",
                  "subType": "TEXT",
                  "model": "type",
                  "label": "global.type",
                  "sortable": false
                },
                {
                  "id": 122,
                  "type": "GRID_COL",
                  "subType": "TEXT",
                  "model": "quantity",
                  "label": "global.quantity",
                  "sortable": false,
                  "dataFormat": "DECIMAL",
                  "formatOptions": {
                    "minimumFractionDigits": 2
                  }
                },
                {
                  "id": 123,
                  "type": "GRID_COL",
                  "subType": "TEXT",
                  "model": "amount",
                  "label": "global.amount",
                  "sortable": false,
                  "dataFormat": "CURRENCY",
                  "formatOptions": {
                    "minimumFractionDigits": 2
                  }
                },
                {
                  "id": 124,
                  "type": "GRID_COL",
                  "subType": "TEXT",
                  "model": "operator",
                  "label": "global.operator",
                  "sortable": false
                },
                {
                  "id": 125,
                  "type": "GRID_COL",
                  "subType": "DATE",
                  "model": "date",
                  "label": "global.date",
                  "sortable": false,
                  "dataFormat": "DATE"
                },
                {
                  "id": 126,
                  "type": "GRID_COL",
                  "subType": "TEXT",
                  "model": "journal",
                  "label": "global.journal",
                  "sortable": false
                }
              ]
            }
          ]
        },
        {
          "id": 129,
          "type": "FIELD_SET",
          "label": "global.sales.rep",
          "children": [
            {
              "id": 130,
              "type": "ROW",
              "children": [
                {
                  "id": 131,
                  "type": "COL",
                  "subType": "1/3",
                  "children": [
                    {
                      "id": 134,
                      "type": "FIELD",
                      "subType": "INFO",
                      "model": "pdhc.poheadermisc.slsnm",
                      "label": "global.name"
                    }
                  ]
                },
                {
                  "id": 133,
                  "type": "COL",
                  "subType": "1/3",
                  "children": [
                    {
                      "id": 135,
                      "type": "FIELD",
                      "subType": "INFO",
                      "model": "pdhc.poheadermisc.slsphoneno",
                      "label": "global.phone.number",
                      "dataFormat": "PHONE"
                    }
                  ]
                },
                {
                  "id": 132,
                  "type": "COL",
                  "subType": "1/3"
                }
              ]
            }
          ]
        },
        {
          "id": 136,
          "type": "FIELD_SET",
          "label": "global.expeditor",
          "children": [
            {
              "id": 137,
              "type": "ROW",
              "children": [
                {
                  "id": 138,
                  "type": "COL",
                  "subType": "1/3",
                  "children": [
                    {
                      "id": 141,
                      "type": "FIELD",
                      "subType": "INFO",
                      "model": "pdhc.poheadermisc.expednm",
                      "label": "global.name"
                    }
                  ]
                },
                {
                  "id": 140,
                  "type": "COL",
                  "subType": "1/3",
                  "children": [
                    {
                      "id": 142,
                      "type": "FIELD",
                      "subType": "INFO",
                      "model": "pdhc.poheadermisc.exphoneno",
                      "label": "global.phone.number",
                      "dataFormat": "PHONE"
                    }
                  ]
                },
                {
                  "id": 139,
                  "type": "COL",
                  "subType": "1/3"
                }
              ]
            }
          ]
        }
      ]
    },
    {
      "id": 143,
      "type": "EXP_AREA",
      "label": "global.ship.from.info",
      "children": [
        {
          "id": 144,
          "type": "ROW",
          "children": [
            {
              "id": 145,
              "type": "COL",
              "subType": "1/3",
              "children": [
                {
                  "id": 148,
                  "type": "FIELD",
                  "subType": "INFO",
                  "model": "pdhc.poheader.shipfm",
                  "label": "global.from",
                  "hyperlinks": {
                    "data": {
                      "stateRef": "apiv.detail({pk: pdhc.poeh.vendno, pk2: pdhc.poeh.shipfmno})"
                    }
                  }
                }
              ]
            },
            {
              "id": 147,
              "type": "COL",
              "subType": "1/3",
              "children": [
                {
                  "id": 149,
                  "type": "CUSTOM",
                  "subType": "AddressInfo",
                  "options": {
                    "countryCdVisible": true,
                    "addressLabel": "global.address",
                    "addr1Model": "pdhc.poheader.fromaddr1",
                    "addr2Model": "pdhc.poheader.fromaddr2",
                    "addr3Model": "pdhc.poheader.fromaddr3",
                    "cityModel": "pdhc.poheader.fromcity",
                    "stateModel": "pdhc.poheader.fromstate",
                    "zipCodeModel": "pdhc.poheader.fromzip",
                    "countryCodeModel": "pdhc.poheader.fromcountrycd"
                  }
                }
              ]
            },
            {
              "id": 146,
              "type": "COL",
              "subType": "1/3",
              "children": [
                {
                  "id": 150,
                  "type": "FIELD",
                  "subType": "INFO",
                  "model": "pdhc.poheader.fromphone",
                  "label": "global.phone.number",
                  "dataFormat": "PHONE"
                },
                {
                  "id": 151,
                  "type": "FIELD",
                  "subType": "INFO",
                  "model": "pdhc.poheader.fromfax",
                  "label": "global.fax.number"
                }
              ]
            }
          ]
        }
      ]
    }
  ]
}