{
  "viewId": "twl-twlail-detail",
  "id": 1,
  "type": "VIEW",
  "subType": "DETAIL",
  "children": [
    {
      "id": 2,
      "type": "FORM",
      "children": [
        {
          "id": 3,
          "type": "MOD_CNTR",
          "controls": {
            "toolbar": {
              "id": 4,
              "type": "TOOLBAR",
              "label": "global.interface.details",
              "subLabel": "{{dtl.getSubTitle()}}",
              "controls": {
                "navBtns": {
                  "id": 5,
                  "type": "BTN_SET",
                  "subType": "TBAR_NAV",
                  "children": [
                    {
                      "id": 6,
                      "type": "BTN",
                      "subType": "ICON",
                      "label": "special.button.back",
                      "icon": "icon-left-arrow",
                      "stateRef": "^.master"
                    }
                  ]
                }
              }
            },
            "content": {
              "id": 7,
              "type": "MOD_CONTENT",
              "children": [
                {
                  "id": 9,
                  "type": "GRID",
                  "model": "dtl.dataset",
                  "controlRef": "dtl.grid",
                  "options": {
                    "editable": false
                  },
                  "controls": {
                    "toolbar": {
                      "id": 17,
                      "type": "TOOLBAR",
                      "label": "global.interfaces"
                    }
                  },
                  "children": [
                    {
                      "id": 10,
                      "type": "GRID_COL",
                      "subType": "TEXT",
                      "model": "recordType",
                      "label": "global.type"
                    },
                    {
                      "id": 11,
                      "type": "GRID_COL",
                      "subType": "CHECKBOX",
                      "model": "active",
                      "label": "global.active",
                      "dataFormat": "LOGICAL"
                    },
                    {
                      "id": 12,
                      "type": "GRID_COL",
                      "subType": "TEXT",
                      "model": "fieldName",
                      "label": "global.field.name"
                    },
                    {
                      "id": 13,
                      "type": "GRID_COL",
                      "subType": "TEXT",
                      "model": "fieldStart",
                      "label": "global.start"
                    },
                    {
                      "id": 14,
                      "type": "GRID_COL",
                      "subType": "TEXT",
                      "model": "fieldLength",
                      "label": "global.length"
                    },
                    {
                      "id": 15,
                      "type": "GRID_COL",
                      "subType": "TEXT",
                      "model": "procedureName",
                      "label": "global.proc"
                    },
                    {
                      "id": 16,
                      "type": "GRID_COL",
                      "subType": "CHECKBOX",
                      "model": "addInReply",
                      "label": "global.reply",
                      "dataFormat": "LOGICAL"
                    }
                  ]
                }
              ]
            }
          }
        }
      ]
    }
  ]
}