{
  "viewId": "va-vasp-tabs-sections-autocreate",
  "id": 1,
  "type": "MODAL",
  "subType": "MODAL",
  "label": "global.auto.create.inventory.component.section",
  "controls": {
    "body": {
      "id": 2,
      "type": "MODAL_BODY",
      "children": [
        {
          "id": 6,
          "type": "FIELD",
          "subType": "DROP_DOWN",
          "model": "auto.vaspSectionAutoCrt.sctncode",
          "label": "global.section.code",
          "type3": "MANUAL",
          "optionLabelField": "descrip",
          "optionValueField": "codeval",
          "optionsModel": "auto.sectionCodes",
          "required": true,
          "blankOption": false
        }
      ]
    },
    "btnSet": {
      "id": 3,
      "type": "BTN_SET",
      "subType": "MODAL",
      "children": [
        {
          "id": 4,
          "type": "BTN",
          "subType": "MODAL_SEC",
          "label": "global.cancel",
          "eventClick": "auto.cancel()"
        },
        {
          "id": 5,
          "type": "BTN",
          "subType": "MODAL_PRI",
          "label": "global.ok",
          "submitForm": true,
          "eventValidated": "auto.submit()"
        }
      ]
    }
  }
}