{
  "viewId": "ao-ao-documents-salesorders-salesorders-soprocessing",
  "id": 1,
  "type": "VIEW",
  "subType": "",
  "children": [
    {
      "id": 5,
      "type": "FIELD_SET",
      "label": "global.interfaces",
      "children": [
        {
          "id": 3,
          "type": "ROW",
          "children": [
            {
              "id": 4,
              "type": "COL",
              "subType": "1/2",
              "children": [
                {
                  "id": 6,
                  "type": "FIELD",
                  "subType": "CHECKBOX",
                  "model": "sodtl.aoSalesOrder.oEPOFl",
                  "label": "global.interface.to.purchase.orders",
                  "dataFormat": "LOGICAL"
                },
                {
                  "id": 7,
                  "type": "FIELD",
                  "subType": "CHECKBOX",
                  "model": "sodtl.aoSalesOrder.oEWTFL",
                  "label": "global.interface.to.warehouse.transfers",
                  "dataFormat": "LOGICAL"
                }
              ]
            },
            {
              "id": 8,
              "type": "COL",
              "subType": "1/2",
              "children": [
                {
                  "id": 11,
                  "type": "FIELD",
                  "subType": "DROP_DOWN",
                  "model": "sodtl.aoSalesOrder.dnrwttiety",
                  "label": "global.allow.do.not.reorder.whse.transfer.tie.by",
                  "type3": "SET",
                  "metaGroup": "COMMON",
                  "meta": "WarehouseTransferTieBy",
                  "blankOption": false,
                  "size": "SM"
                }
              ]
            }
          ]
        }
      ]
    },
    {
      "id": 12,
      "type": "FIELD_SET",
      "label": "global.calculations",
      "children": [
        {
          "id": 13,
          "type": "ROW",
          "children": [
            {
              "id": 14,
              "type": "COL",
              "subType": "1/2",
              "children": [
                {
                  "id": 16,
                  "type": "FIELD",
                  "subType": "DROP_DOWN",
                  "model": "sodtl.aoSalesOrder.oEvrebcalcty",
                  "label": "global.calculate.vendor.rebate.at",
                  "type3": "SET",
                  "metaGroup": "COMMON",
                  "meta": "VendorRebateAt",
                  "blankOption": false,
                  "size": "SM"
                },
                {
                  "id": 17,
                  "type": "FIELD",
                  "subType": "DROP_DOWN",
                  "model": "sodtl.aoSalesOrder.oEfrzrebty",
                  "label": "global.recalc.rebate.through",
                  "type3": "SET",
                  "metaGroup": "COMMON",
                  "meta": "RebateThrough",
                  "blankOption": false,
                  "size": "SM"
                }
              ]
            },
            {
              "id": 15,
              "type": "COL",
              "subType": "1/2",
              "children": [
                {
                  "id": 18,
                  "type": "FIELD",
                  "subType": "DROP_DOWN",
                  "model": "sodtl.aoSalesOrder.oECostSale",
                  "label": "global.to.calculate.margin.percent.divide.by",
                  "type3": "SET",
                  "metaGroup": "COMMON",
                  "meta": "MarginPerCentageDivideBy",
                  "blankOption": false,
                  "size": "SM"
                },
                {
                  "id": 19,
                  "type": "FIELD",
                  "subType": "DROP_DOWN",
                  "model": "sodtl.aoSalesOrder.emoemarginty",
                  "label": "global.event.manager.trigger.calculate.oe.header.margin.",
                  "type3": "SET",
                  "metaGroup": "COMMON",
                  "meta": "EventManagerTriggerBy",
                  "blankOption": false,
                  "size": "SM"
                },
                {
                  "id": 38,
                  "type": "FIELD",
                  "subType": "CHECKBOX",
                  "model": "sodtl.aoSalesOrder.pDCalcPBKitRebSale",
                  "label": "global.roll.rebated.price.on.prebuilt.kits",
                  "dataFormat": "LOGICAL"
                }
              ]
            }
          ]
        }
      ]
    },
    {
      "id": 20,
      "type": "FIELD_SET",
      "label": "global.workflow",
      "children": [
        {
          "id": 21,
          "type": "ROW",
          "children": [
            {
              "id": 22,
              "type": "COL",
              "subType": "1/2",
              "children": [
                {
                  "id": 24,
                  "type": "FIELD",
                  "subType": "CHECKBOX",
                  "model": "sodtl.aoSalesOrder.csbofl",
                  "label": "{{sodtl.aoSalesOrder.csbofllabel}}",
                  "dataFormat": "LOGICAL"
                },
                {
                  "id": 37,
                  "type": "FIELD",
                  "subType": "CHECKBOX",
                  "model": "sodtl.aoSalesOrder.oeescodaddonfl",
                  "label": "global.calculate.cod.addon.in.standard.shipping",
                  "dataFormat": "LOGICAL"
                },
                {
                  "id": 26,
                  "type": "FIELD",
                  "subType": "TEXT_BOX",
                  "model": "sodtl.aoSalesOrder.oewriteamt",
                  "label": "global.downpayment.write.off.amount",
                  "type3": "SET",
                  "metaGroup": "COMMON",
                  "meta": "WarehouseTransferTieBy",
                  "dataFormat": "DECIMAL",
                  "digits": 7,
                  "decimals": 2,
                  "sign": "+",
                  "size": "SM",
                  "formatOptions": {
                    "minimumFractionDigits": 2,
                    "maximumFractionDigits": 2
                  }
                }
              ]
            },
            {
              "id": 23,
              "type": "COL",
              "subType": "1/2",
              "children": [
                {
                  "id": 25,
                  "type": "FIELD",
                  "subType": "TEXT_BOX",
                  "model": "sodtl.aoSalesOrder.oefutdays",
                  "label": "global.conversion.days.for.changing.future.and.blanket.or",
                  "type3": "SET",
                  "metaGroup": "COMMON",
                  "meta": "WarehouseTransferTieBy",
                  "dataFormat": "INTEGER",
                  "digits": 2,
                  "sign": "+",
                  "size": "XS"
                },
                {
                  "id": 27,
                  "type": "FIELD",
                  "subType": "LOOKUP",
                  "model": "sodtl.aoSalesOrder.oECombinedShipment",
                  "label": "global.combined.shipment",
                  "type3": "SET",
                  "metaGroup": "COMMON",
                  "meta": "ShipVia"
                }
              ]
            }
          ]
        }
      ]
    },
    {
      "id": 28,
      "type": "FIELD_SET",
      "label": "global.supplier.access",
      "children": [
        {
          "id": 29,
          "type": "ROW",
          "children": [
            {
              "id": 30,
              "type": "COL",
              "subType": "1/2",
              "children": [
                {
                  "id": 31,
                  "type": "FIELD",
                  "subType": "TEXT_BOX",
                  "model": "sodtl.aoSalesOrder.httpservername",
                  "label": "global.host.name",
                  "type3": "SET",
                  "metaGroup": "COMMON",
                  "meta": "WarehouseTransferTieBy"
                },
                {
                  "id": 34,
                  "type": "FIELD",
                  "subType": "TEXT_BOX",
                  "model": "sodtl.aoSalesOrder.httpserverportnumber",
                  "label": "global.port.number",
                  "type3": "SET",
                  "metaGroup": "COMMON",
                  "meta": "WarehouseTransferTieBy",
                  "dataFormat": "INTEGER_TEXT",
                  "sign": "+",
                  "digits": 5,
                  "size": "SM"
                },
                {
                  "id": 36,
                  "type": "FIELD",
                  "subType": "CHECKBOX",
                  "model": "sodtl.aoSalesOrder.keepreqrecords",
                  "label": "global.keep.records",
                  "dataFormat": "LOGICAL"
                }
              ]
            },
            {
              "id": 32,
              "type": "COL",
              "subType": "1/2",
              "children": [
                {
                  "id": 33,
                  "type": "FIELD",
                  "subType": "TEXT_BOX",
                  "model": "sodtl.aoSalesOrder.pauseseconds",
                  "label": "global.seconds.to.pause",
                  "type3": "SET",
                  "metaGroup": "COMMON",
                  "meta": "WarehouseTransferTieBy",
                  "dataFormat": "INTEGER_TEXT",
                  "digits": 6,
                  "sign": "+",
                  "size": "XS"
                },
                {
                  "id": 35,
                  "type": "FIELD",
                  "subType": "TEXT_BOX",
                  "model": "sodtl.aoSalesOrder.pausetimes",
                  "label": "global.time.to.pause",
                  "type3": "SET",
                  "metaGroup": "COMMON",
                  "meta": "WarehouseTransferTieBy",
                  "dataFormat": "INTEGER_TEXT",
                  "sign": "+",
                  "digits": 6,
                  "size": "XS"
                }
              ]
            }
          ]
        }
      ]
    }
  ]
}